cas/__init__.py
cas/base/__init__.py
cas/base/constant.py
cas/base/enum.py
cas/base/exception.py
cas/base/logger.py
cas/base/message.py
cas/base/schemas.py
cas/base/tro.py
cas/base/validator.py
cas/client/__init__.py
cas/client/cfr2.py
cas/client/elasticsearch.py
cas/client/http.py
cas/client/redis.py
cas/client/websocket.py
cas/utils/__init__.py
cas/utils/aes_crypto.py
cas/utils/des_crypto.py
cas/utils/gzip_crypto.py
cas/utils/rsa_crypto.py
cas_base-1.6.2.dist-info/METADATA
cas_base-1.6.2.dist-info/WHEEL
cas_base-1.6.2.dist-info/top_level.txt
cas_base-1.6.2.dist-info/RECORD
