Metadata-Version: 2.1
Name: cas-base
Version: 1.6.2
Summary: cas-base
Author: xxoo
Author-email: xxoo@example.com
Requires-Dist: pydantic==2.8.2
Requires-Dist: pydantic-settings==2.4.0
Requires-Dist: pydantic-core==2.20.1
Requires-Dist: websockets==10.4
Requires-Dist: requests==2.31.0
Requires-Dist: loguru==0.7.2
Requires-Dist: PyJWT==2.8.0
Requires-Dist: pycryptodome==3.19.1
Requires-Dist: redis==5.1.1
Requires-Dist: elasticsearch==8.15.1
Requires-Dist: psutil==5.9.8
